{
	"configurations" : 
	[
		{
			"directories" : 
			[
				{
					"build" : ".",
					"jsonFile" : "directory-.-Debug-f5ebdc15457944623624.json",
					"minimumCMakeVersion" : 
					{
						"string" : "3.0.0"
					},
					"projectIndex" : 0,
					"source" : ".",
					"targetIndexes" : 
					[
						0,
						1,
						2,
						3,
						4,
						5,
						6,
						7,
						8,
						9,
						10,
						11,
						12,
						13,
						14,
						15,
						16,
						17,
						18,
						19,
						20,
						21,
						22,
						23,
						24,
						25,
						26,
						27,
						28,
						29
					]
				}
			],
			"name" : "Debug",
			"projects" : 
			[
				{
					"directoryIndexes" : 
					[
						0
					],
					"name" : "ACWING",
					"targetIndexes" : 
					[
						0,
						1,
						2,
						3,
						4,
						5,
						6,
						7,
						8,
						9,
						10,
						11,
						12,
						13,
						14,
						15,
						16,
						17,
						18,
						19,
						20,
						21,
						22,
						23,
						24,
						25,
						26,
						27,
						28,
						29
					]
				}
			],
			"targets" : 
			[
				{
					"directoryIndex" : 0,
					"id" : "Continuous::@6890427a1f51a3e7e1df",
					"jsonFile" : "target-Continuous-Debug-fc82ef98f48dcab4753e.json",
					"name" : "Continuous",
					"projectIndex" : 0
				},
				{
					"directoryIndex" : 0,
					"id" : "ContinuousBuild::@6890427a1f51a3e7e1df",
					"jsonFile" : "target-ContinuousBuild-Debug-68d658aab75ada64f27b.json",
					"name" : "ContinuousBuild",
					"projectIndex" : 0
				},
				{
					"directoryIndex" : 0,
					"id" : "ContinuousConfigure::@6890427a1f51a3e7e1df",
					"jsonFile" : "target-ContinuousConfigure-Debug-0c0da4247ff50f85ba3b.json",
					"name" : "ContinuousConfigure",
					"projectIndex" : 0
				},
				{
					"directoryIndex" : 0,
					"id" : "ContinuousCoverage::@6890427a1f51a3e7e1df",
					"jsonFile" : "target-ContinuousCoverage-Debug-70eff746c3ee351d0933.json",
					"name" : "ContinuousCoverage",
					"projectIndex" : 0
				},
				{
					"directoryIndex" : 0,
					"id" : "ContinuousMemCheck::@6890427a1f51a3e7e1df",
					"jsonFile" : "target-ContinuousMemCheck-Debug-387b5d404a29277f0f92.json",
					"name" : "ContinuousMemCheck",
					"projectIndex" : 0
				},
				{
					"directoryIndex" : 0,
					"id" : "ContinuousStart::@6890427a1f51a3e7e1df",
					"jsonFile" : "target-ContinuousStart-Debug-489b007242ccd6be023e.json",
					"name" : "ContinuousStart",
					"projectIndex" : 0
				},
				{
					"directoryIndex" : 0,
					"id" : "ContinuousSubmit::@6890427a1f51a3e7e1df",
					"jsonFile" : "target-ContinuousSubmit-Debug-8d2de5acb888875a2c29.json",
					"name" : "ContinuousSubmit",
					"projectIndex" : 0
				},
				{
					"directoryIndex" : 0,
					"id" : "ContinuousTest::@6890427a1f51a3e7e1df",
					"jsonFile" : "target-ContinuousTest-Debug-28aaba67538294456de7.json",
					"name" : "ContinuousTest",
					"projectIndex" : 0
				},
				{
					"directoryIndex" : 0,
					"id" : "ContinuousUpdate::@6890427a1f51a3e7e1df",
					"jsonFile" : "target-ContinuousUpdate-Debug-0d9a453d617bc7ab435a.json",
					"name" : "ContinuousUpdate",
					"projectIndex" : 0
				},
				{
					"directoryIndex" : 0,
					"id" : "Experimental::@6890427a1f51a3e7e1df",
					"jsonFile" : "target-Experimental-Debug-66b023448c19e9fe4ca6.json",
					"name" : "Experimental",
					"projectIndex" : 0
				},
				{
					"directoryIndex" : 0,
					"id" : "ExperimentalBuild::@6890427a1f51a3e7e1df",
					"jsonFile" : "target-ExperimentalBuild-Debug-bcd7111cfa89ddc3d050.json",
					"name" : "ExperimentalBuild",
					"projectIndex" : 0
				},
				{
					"directoryIndex" : 0,
					"id" : "ExperimentalConfigure::@6890427a1f51a3e7e1df",
					"jsonFile" : "target-ExperimentalConfigure-Debug-9f304a9f2e2a0c4116a9.json",
					"name" : "ExperimentalConfigure",
					"projectIndex" : 0
				},
				{
					"directoryIndex" : 0,
					"id" : "ExperimentalCoverage::@6890427a1f51a3e7e1df",
					"jsonFile" : "target-ExperimentalCoverage-Debug-11eb9d45108c5f9762a5.json",
					"name" : "ExperimentalCoverage",
					"projectIndex" : 0
				},
				{
					"directoryIndex" : 0,
					"id" : "ExperimentalMemCheck::@6890427a1f51a3e7e1df",
					"jsonFile" : "target-ExperimentalMemCheck-Debug-0ceeb3082f5fb4a4c16b.json",
					"name" : "ExperimentalMemCheck",
					"projectIndex" : 0
				},
				{
					"directoryIndex" : 0,
					"id" : "ExperimentalStart::@6890427a1f51a3e7e1df",
					"jsonFile" : "target-ExperimentalStart-Debug-ac1b17b05626f6f45976.json",
					"name" : "ExperimentalStart",
					"projectIndex" : 0
				},
				{
					"directoryIndex" : 0,
					"id" : "ExperimentalSubmit::@6890427a1f51a3e7e1df",
					"jsonFile" : "target-ExperimentalSubmit-Debug-3d80c0f5ba3971fd885e.json",
					"name" : "ExperimentalSubmit",
					"projectIndex" : 0
				},
				{
					"directoryIndex" : 0,
					"id" : "ExperimentalTest::@6890427a1f51a3e7e1df",
					"jsonFile" : "target-ExperimentalTest-Debug-d1173839e5f31e0af464.json",
					"name" : "ExperimentalTest",
					"projectIndex" : 0
				},
				{
					"directoryIndex" : 0,
					"id" : "ExperimentalUpdate::@6890427a1f51a3e7e1df",
					"jsonFile" : "target-ExperimentalUpdate-Debug-c643df78ed510d1a33b8.json",
					"name" : "ExperimentalUpdate",
					"projectIndex" : 0
				},
				{
					"directoryIndex" : 0,
					"id" : "Nightly::@6890427a1f51a3e7e1df",
					"jsonFile" : "target-Nightly-Debug-56da14170ead07b828a0.json",
					"name" : "Nightly",
					"projectIndex" : 0
				},
				{
					"directoryIndex" : 0,
					"id" : "NightlyBuild::@6890427a1f51a3e7e1df",
					"jsonFile" : "target-NightlyBuild-Debug-b4985b076854410d0bf7.json",
					"name" : "NightlyBuild",
					"projectIndex" : 0
				},
				{
					"directoryIndex" : 0,
					"id" : "NightlyConfigure::@6890427a1f51a3e7e1df",
					"jsonFile" : "target-NightlyConfigure-Debug-22d5bd76b925e3d536be.json",
					"name" : "NightlyConfigure",
					"projectIndex" : 0
				},
				{
					"directoryIndex" : 0,
					"id" : "NightlyCoverage::@6890427a1f51a3e7e1df",
					"jsonFile" : "target-NightlyCoverage-Debug-e22f63eb189d9098a436.json",
					"name" : "NightlyCoverage",
					"projectIndex" : 0
				},
				{
					"directoryIndex" : 0,
					"id" : "NightlyMemCheck::@6890427a1f51a3e7e1df",
					"jsonFile" : "target-NightlyMemCheck-Debug-87d9d11855d803d832f8.json",
					"name" : "NightlyMemCheck",
					"projectIndex" : 0
				},
				{
					"directoryIndex" : 0,
					"id" : "NightlyMemoryCheck::@6890427a1f51a3e7e1df",
					"jsonFile" : "target-NightlyMemoryCheck-Debug-13a356672802eac2f9a7.json",
					"name" : "NightlyMemoryCheck",
					"projectIndex" : 0
				},
				{
					"directoryIndex" : 0,
					"id" : "NightlyStart::@6890427a1f51a3e7e1df",
					"jsonFile" : "target-NightlyStart-Debug-231ce97bd6a57278aff2.json",
					"name" : "NightlyStart",
					"projectIndex" : 0
				},
				{
					"directoryIndex" : 0,
					"id" : "NightlySubmit::@6890427a1f51a3e7e1df",
					"jsonFile" : "target-NightlySubmit-Debug-234822cd9f98b074471c.json",
					"name" : "NightlySubmit",
					"projectIndex" : 0
				},
				{
					"directoryIndex" : 0,
					"id" : "NightlyTest::@6890427a1f51a3e7e1df",
					"jsonFile" : "target-NightlyTest-Debug-a658f6b5ad13bea7a6a8.json",
					"name" : "NightlyTest",
					"projectIndex" : 0
				},
				{
					"directoryIndex" : 0,
					"id" : "NightlyUpdate::@6890427a1f51a3e7e1df",
					"jsonFile" : "target-NightlyUpdate-Debug-04824b460d585f621125.json",
					"name" : "NightlyUpdate",
					"projectIndex" : 0
				},
				{
					"directoryIndex" : 0,
					"id" : "algo_main::@6890427a1f51a3e7e1df",
					"jsonFile" : "target-algo_main-Debug-8b1814ed9f2bafd17255.json",
					"name" : "algo_main",
					"projectIndex" : 0
				},
				{
					"directoryIndex" : 0,
					"id" : "main::@6890427a1f51a3e7e1df",
					"jsonFile" : "target-main-Debug-5457faf79e2c63cf8984.json",
					"name" : "main",
					"projectIndex" : 0
				}
			]
		}
	],
	"kind" : "codemodel",
	"paths" : 
	{
		"build" : "/Users/Lavender/Desktop/Go项目/Go-for-Acwing/build",
		"source" : "/Users/Lavender/Desktop/Go项目/Go-for-Acwing"
	},
	"version" : 
	{
		"major" : 2,
		"minor" : 3
	}
}
